openbb_stocks/__init__.py
openbb_stocks/ca/__init__.py
openbb_stocks/ca/ca_router.py
openbb_stocks/disc/__init__.py
openbb_stocks/disc/disc_router.py
openbb_stocks/dps/__init__.py
openbb_stocks/dps/dps_router.py
openbb_stocks/fa/__init__.py
openbb_stocks/fa/fa_router.py
openbb_stocks/gov/__init__.py
openbb_stocks/gov/gov_router.py
openbb_stocks/ins/__init__.py
openbb_stocks/ins/ins_router.py
openbb_stocks/options/__init__.py
openbb_stocks/options/options_router.py
openbb_stocks/py.typed
openbb_stocks/stocks_router.py
openbb_stocks-0.1.0a5.dist-info/METADATA
openbb_stocks-0.1.0a5.dist-info/WHEEL
openbb_stocks-0.1.0a5.dist-info/entry_points.txt
openbb_stocks-0.1.0a5.dist-info/RECORD
