Metadata-Version: 2.1
Name: openbb-stocks
Version: 0.1.0a5
Summary: Stocks extension for OpenBB
Author: OpenBB Team
Author-email: hello@openbb.co
Requires-Python: >=3.8,<4.0
Classifier: Programming Language :: Python :: 3
Classifier: Programming Language :: Python :: 3.8
Classifier: Programming Language :: Python :: 3.9
Classifier: Programming Language :: Python :: 3.10
Classifier: Programming Language :: Python :: 3.11
Classifier: Programming Language :: Python :: 3.12
Requires-Dist: openbb-core (>=0.1.0a5,<0.2.0)
